{"Key":467,"Weenies":[{"WCID":1363,"Position":{"ObjCellID":30605580,"Origin":{"X":10.0,"Y":-20.0,"Z":0.0},"Angles":{"W":1.0,"X":0.0,"Y":0.0,"Z":0.0}},"ID":1880961024},{"WCID":396,"Position":{"ObjCellID":30605586,"Origin":{"X":2.1605,"Y":0.737083,"Z":6.0},"Angles":{"W":1.0,"X":0.0,"Y":0.0,"Z":0.0}},"ID":1880961025},{"WCID":907,"Position":{"ObjCellID":30605594,"Origin":{"X":19.2034,"Y":-10.4107,"Z":6.0},"Angles":{"W":1.0,"X":0.0,"Y":0.0,"Z":0.0}},"ID":1880961026},{"WCID":1129,"Position":{"ObjCellID":30605620,"Origin":{"X":12.4493,"Y":-20.8427,"Z":30.0},"Angles":{"W":1.0,"X":0.0,"Y":0.0,"Z":0.0}},"ID":1880961027},{"WCID":4024,"Position":{"ObjCellID":30605620,"Origin":{"X":9.83726,"Y":-19.5373,"Z":30.0},"Angles":{"W":1.0,"X":0.0,"Y":0.0,"Z":0.0}},"ID":1880961028},{"WCID":911,"Position":{"ObjCellID":30605620,"Origin":{"X":7.30273,"Y":-22.2987,"Z":30.0},"Angles":{"W":1.0,"X":0.0,"Y":0.0,"Z":0.0}},"ID":1880961029},{"WCID":964,"Position":{"ObjCellID":30605636,"Origin":{"X":2.02147,"Y":-12.8264,"Z":48.0},"Angles":{"W":-4.37114E-08,"X":0.0,"Y":0.0,"Z":-1.0}},"ID":1880961030},{"WCID":905,"Position":{"ObjCellID":30605645,"Origin":{"X":21.7387,"Y":-1.87958,"Z":48.0},"Angles":{"W":-0.707107,"X":0.0,"Y":0.0,"Z":-0.707107}},"ID":1880961031},{"WCID":964,"Position":{"ObjCellID":30605649,"Origin":{"X":22.3037,"Y":-7.02419,"Z":48.0},"Angles":{"W":1.0,"X":0.0,"Y":0.0,"Z":0.0}},"ID":1880961032},{"WCID":964,"Position":{"ObjCellID":30605661,"Origin":{"X":9.01683,"Y":2.46015,"Z":60.0},"Angles":{"W":-0.707107,"X":0.0,"Y":0.0,"Z":-0.707107}},"ID":1880961033},{"WCID":964,"Position":{"ObjCellID":30605661,"Origin":{"X":10.663,"Y":-3.341,"Z":60.0},"Angles":{"W":0.707107,"X":0.0,"Y":0.0,"Z":-0.707107}},"ID":1880961034},{"WCID":964,"Position":{"ObjCellID":30605664,"Origin":{"X":22.7686,"Y":-7.30546,"Z":60.0},"Angles":{"W":-4.37114E-08,"X":0.0,"Y":0.0,"Z":-1.0}},"ID":1880961035},{"WCID":905,"Position":{"ObjCellID":30605695,"Origin":{"X":8.04508,"Y":-1.86836,"Z":84.0},"Angles":{"W":-0.707107,"X":0.0,"Y":0.0,"Z":-0.707107}},"ID":1880961036},{"WCID":905,"Position":{"ObjCellID":30605695,"Origin":{"X":10.492,"Y":4.19239,"Z":84.0},"Angles":{"W":0.0316289,"X":0.0,"Y":0.0,"Z":-0.9995}},"ID":1880961037},{"WCID":905,"Position":{"ObjCellID":30605698,"Origin":{"X":18.1772,"Y":-10.577,"Z":84.0},"Angles":{"W":-4.37114E-08,"X":0.0,"Y":0.0,"Z":-1.0}},"ID":1880961038},{"WCID":905,"Position":{"ObjCellID":30605698,"Origin":{"X":22.99,"Y":-8.44989,"Z":84.0},"Angles":{"W":-4.37114E-08,"X":0.0,"Y":0.0,"Z":-1.0}},"ID":1880961039},{"WCID":1130,"Position":{"ObjCellID":30605743,"Origin":{"X":11.7638,"Y":0.406426,"Z":114.0},"Angles":{"W":-4.37114E-08,"X":0.0,"Y":0.0,"Z":-1.0}},"ID":1880961040},{"WCID":4021,"Position":{"ObjCellID":30605743,"Origin":{"X":8.13556,"Y":1.30476,"Z":114.0},"Angles":{"W":-4.37114E-08,"X":0.0,"Y":0.0,"Z":-1.0}},"ID":1880961041},{"WCID":4011,"Position":{"ObjCellID":30605743,"Origin":{"X":12.1384,"Y":-2.22952,"Z":114.0},"Angles":{"W":-4.37114E-08,"X":0.0,"Y":0.0,"Z":-1.0}},"ID":1880961042},{"WCID":911,"Position":{"ObjCellID":30605743,"Origin":{"X":12.3774,"Y":3.13762,"Z":114.0},"Angles":{"W":-4.37114E-08,"X":0.0,"Y":0.0,"Z":-1.0}},"ID":1880961043},{"WCID":369,"Position":{"ObjCellID":30605756,"Origin":{"X":9.84015,"Y":-3.71487,"Z":120.0},"Angles":{"W":1.0,"X":0.0,"Y":0.0,"Z":-4.37114E-08}},"ID":1880961044}]}