{"Key":688,"Weenies":[{"WCID":22900,"Position":{"ObjCellID":45089024,"Origin":{"X":112.303,"Y":-60.6616,"Z":-5.995},"Angles":{"W":-0.71514,"X":0.0,"Y":0.0,"Z":0.698981}},"ID":1881866443},{"WCID":8851,"Position":{"ObjCellID":45089028,"Origin":{"X":130.0,"Y":-39.426,"Z":-5.995},"Angles":{"W":1.0,"X":0.0,"Y":0.0,"Z":0.0}},"ID":1881866241},{"WCID":7983,"Position":{"ObjCellID":45089028,"Origin":{"X":129.17,"Y":-42.0792,"Z":-5.995},"Angles":{"W":-0.014872,"X":0.0,"Y":0.0,"Z":0.999889}},"ID":1881866242},{"WCID":7923,"Position":{"ObjCellID":45089030,"Origin":{"X":129.639,"Y":-62.7068,"Z":-6.0},"Angles":{"W":1.0,"X":0.0,"Y":0.0,"Z":0.0}},"ID":1881866243},{"WCID":4219,"Position":{"ObjCellID":45089030,"Origin":{"X":132.434,"Y":-62.8905,"Z":-5.995},"Angles":{"W":0.035739,"X":0.0,"Y":0.0,"Z":-0.999361}},"ID":1881866244},{"WCID":7925,"Position":{"ObjCellID":45089031,"Origin":{"X":127.138,"Y":-70.4555,"Z":-5.995},"Angles":{"W":-0.98877,"X":0.0,"Y":0.0,"Z":0.149446}},"ID":1881866245},{"WCID":9000,"Position":{"ObjCellID":45089032,"Origin":{"X":129.709,"Y":-80.2786,"Z":-5.995},"Angles":{"W":-0.00321396,"X":0.0,"Y":0.0,"Z":0.999995}},"ID":1881866246},{"WCID":8822,"Position":{"ObjCellID":45089032,"Origin":{"X":129.991,"Y":-77.0294,"Z":-5.995},"Angles":{"W":-0.999997,"X":0.0,"Y":0.0,"Z":0.00226004}},"ID":1881866247},{"WCID":22900,"Position":{"ObjCellID":45089036,"Origin":{"X":147.961,"Y":-60.0662,"Z":-5.995},"Angles":{"W":0.744059,"X":0.0,"Y":0.0,"Z":0.668114}},"ID":1881866444},{"WCID":8516,"Position":{"ObjCellID":45089043,"Origin":{"X":130.0,"Y":-60.0,"Z":6.0},"Angles":{"W":1.0,"X":0.0,"Y":0.0,"Z":0.0}},"ID":1881866249},{"WCID":7983,"Position":{"ObjCellID":45089064,"Origin":{"X":117.133,"Y":-59.9784,"Z":12.005},"Angles":{"W":0.717663,"X":0.0,"Y":0.0,"Z":-0.696391}},"ID":1881866250},{"WCID":23091,"Position":{"ObjCellID":45089064,"Origin":{"X":123.13,"Y":-55.9881,"Z":12.0055},"Angles":{"W":0.999049,"X":0.0,"Y":0.0,"Z":0.043597}},"ID":1881866251},{"WCID":23091,"Position":{"ObjCellID":45089064,"Origin":{"X":123.539,"Y":-64.0657,"Z":12.0055},"Angles":{"W":0.059644,"X":0.0,"Y":0.0,"Z":0.99822}},"ID":1881866252},{"WCID":7983,"Position":{"ObjCellID":45089066,"Origin":{"X":130.092,"Y":-47.0682,"Z":12.005},"Angles":{"W":0.035822,"X":0.0,"Y":0.0,"Z":-0.999358}},"ID":1881866253},{"WCID":23091,"Position":{"ObjCellID":45089066,"Origin":{"X":134.33,"Y":-53.43,"Z":12.0055},"Angles":{"W":-0.717864,"X":0.0,"Y":0.0,"Z":0.696183}},"ID":1881866254},{"WCID":23091,"Position":{"ObjCellID":45089066,"Origin":{"X":125.702,"Y":-53.5697,"Z":12.0055},"Angles":{"W":0.707852,"X":0.0,"Y":0.0,"Z":0.70636}},"ID":1881866255},{"WCID":7983,"Position":{"ObjCellID":45089068,"Origin":{"X":129.795,"Y":-72.6222,"Z":12.005},"Angles":{"W":0.99991,"X":0.0,"Y":0.0,"Z":-0.0134336}},"ID":1881866256},{"WCID":23091,"Position":{"ObjCellID":45089068,"Origin":{"X":125.887,"Y":-66.0896,"Z":12.0055},"Angles":{"W":0.664142,"X":0.0,"Y":0.0,"Z":0.747606}},"ID":1881866257},{"WCID":23091,"Position":{"ObjCellID":45089068,"Origin":{"X":134.241,"Y":-66.2208,"Z":12.0055},"Angles":{"W":-0.725918,"X":0.0,"Y":0.0,"Z":0.687781}},"ID":1881866258},{"WCID":7983,"Position":{"ObjCellID":45089070,"Origin":{"X":142.957,"Y":-60.0135,"Z":12.005},"Angles":{"W":0.710673,"X":0.0,"Y":0.0,"Z":0.703522}},"ID":1881866259},{"WCID":23091,"Position":{"ObjCellID":45089070,"Origin":{"X":136.262,"Y":-64.1847,"Z":12.0055},"Angles":{"W":0.02201,"X":0.0,"Y":0.0,"Z":0.999758}},"ID":1881866260},{"WCID":23091,"Position":{"ObjCellID":45089070,"Origin":{"X":136.26,"Y":-55.8573,"Z":12.0055},"Angles":{"W":0.999999,"X":0.0,"Y":0.0,"Z":-0.00121504}},"ID":1881866261},{"WCID":7983,"Position":{"ObjCellID":45089083,"Origin":{"X":40.0623,"Y":-31.3699,"Z":36.1152},"Angles":{"W":-0.021919,"X":0.0,"Y":0.0,"Z":-0.99976}},"ID":1881866262},{"WCID":8887,"Position":{"ObjCellID":45089083,"Origin":{"X":42.8433,"Y":-30.654,"Z":36.005},"Angles":{"W":0.565367,"X":0.0,"Y":0.0,"Z":0.824839}},"ID":1881866263},{"WCID":8887,"Position":{"ObjCellID":45089084,"Origin":{"X":39.8557,"Y":-43.1152,"Z":36.005},"Angles":{"W":-0.999731,"X":0.0,"Y":0.0,"Z":-0.0232051}},"ID":1881866264},{"WCID":8887,"Position":{"ObjCellID":45089085,"Origin":{"X":40.8713,"Y":-38.9855,"Z":36.005},"Angles":{"W":0.999033,"X":0.0,"Y":0.0,"Z":-0.0439693}},"ID":1881866265},{"WCID":8887,"Position":{"ObjCellID":45089086,"Origin":{"X":40.0,"Y":-50.0,"Z":36.0},"Angles":{"W":1.0,"X":0.0,"Y":0.0,"Z":0.0}},"ID":1881866266},{"WCID":8887,"Position":{"ObjCellID":45089086,"Origin":{"X":40.0112,"Y":-52.9829,"Z":36.0},"Angles":{"W":1.0,"X":0.0,"Y":0.0,"Z":0.0}},"ID":1881866267},{"WCID":8887,"Position":{"ObjCellID":45089086,"Origin":{"X":39.9747,"Y":-47.0839,"Z":36.0},"Angles":{"W":1.0,"X":0.0,"Y":0.0,"Z":0.0}},"ID":1881866268},{"WCID":8887,"Position":{"ObjCellID":45089087,"Origin":{"X":40.0,"Y":-60.0,"Z":36.0},"Angles":{"W":1.0,"X":0.0,"Y":0.0,"Z":0.0}},"ID":1881866269},{"WCID":8887,"Position":{"ObjCellID":45089087,"Origin":{"X":40.0384,"Y":-63.4466,"Z":36.005},"Angles":{"W":-0.999748,"X":0.0,"Y":0.0,"Z":-0.022457}},"ID":1881866270},{"WCID":8887,"Position":{"ObjCellID":45089087,"Origin":{"X":36.2951,"Y":-60.0691,"Z":36.005},"Angles":{"W":-0.713976,"X":0.0,"Y":0.0,"Z":-0.70017}},"ID":1881866271},{"WCID":8887,"Position":{"ObjCellID":45089087,"Origin":{"X":43.3378,"Y":-59.9197,"Z":36.005},"Angles":{"W":-0.714866,"X":0.0,"Y":0.0,"Z":0.699262}},"ID":1881866272},{"WCID":8887,"Position":{"ObjCellID":45089087,"Origin":{"X":40.0252,"Y":-56.3595,"Z":36.005},"Angles":{"W":-0.999909,"X":0.0,"Y":0.0,"Z":-0.01349}},"ID":1881866273},{"WCID":8887,"Position":{"ObjCellID":45089092,"Origin":{"X":40.0,"Y":-70.0,"Z":36.0},"Angles":{"W":-4.37114E-08,"X":0.0,"Y":0.0,"Z":-1.0}},"ID":1881866274},{"WCID":8887,"Position":{"ObjCellID":45089092,"Origin":{"X":40.0878,"Y":-66.955,"Z":36.0},"Angles":{"W":-4.37114E-08,"X":0.0,"Y":0.0,"Z":-1.0}},"ID":1881866275},{"WCID":8887,"Position":{"ObjCellID":45089092,"Origin":{"X":39.9484,"Y":-73.0741,"Z":36.0},"Angles":{"W":-4.37114E-08,"X":0.0,"Y":0.0,"Z":-1.0}},"ID":1881866276},{"WCID":8887,"Position":{"ObjCellID":45089093,"Origin":{"X":40.0,"Y":-80.0,"Z":36.0},"Angles":{"W":1.0,"X":0.0,"Y":0.0,"Z":0.0}},"ID":1881866277},{"WCID":8887,"Position":{"ObjCellID":45089094,"Origin":{"X":40.0113,"Y":-77.2834,"Z":36.005},"Angles":{"W":-0.998707,"X":0.0,"Y":0.0,"Z":-0.050838}},"ID":1881866278},{"WCID":7983,"Position":{"ObjCellID":45089095,"Origin":{"X":43.2968,"Y":-86.7347,"Z":37.2252},"Angles":{"W":0.954597,"X":0.0,"Y":0.0,"Z":-0.297899}},"ID":1881866279},{"WCID":8887,"Position":{"ObjCellID":45089095,"Origin":{"X":41.1547,"Y":-89.3333,"Z":36.0},"Angles":{"W":-0.707107,"X":0.0,"Y":0.0,"Z":-0.707107}},"ID":1881866280},{"WCID":8887,"Position":{"ObjCellID":45089097,"Origin":{"X":50.0186,"Y":-23.0261,"Z":36.005},"Angles":{"W":-0.253308,"X":0.0,"Y":0.0,"Z":-0.967386}},"ID":1881866281},{"WCID":8887,"Position":{"ObjCellID":45089098,"Origin":{"X":53.6496,"Y":-20.0798,"Z":36.005},"Angles":{"W":-0.65674,"X":0.0,"Y":0.0,"Z":-0.754117}},"ID":1881866282},{"WCID":8887,"Position":{"ObjCellID":45089099,"Origin":{"X":50.0613,"Y":-27.9195,"Z":36.005},"Angles":{"W":-0.0310943,"X":0.0,"Y":0.0,"Z":-0.999516}},"ID":1881866283},{"WCID":8887,"Position":{"ObjCellID":45089100,"Origin":{"X":49.9228,"Y":-31.5088,"Z":36.005},"Angles":{"W":0.973716,"X":0.0,"Y":0.0,"Z":0.227766}},"ID":1881866284},{"WCID":7983,"Position":{"ObjCellID":45089101,"Origin":{"X":49.5287,"Y":-38.0445,"Z":36.005},"Angles":{"W":-0.520407,"X":0.0,"Y":0.0,"Z":-0.853918}},"ID":1881866285},{"WCID":8887,"Position":{"ObjCellID":45089101,"Origin":{"X":47.2502,"Y":-38.6901,"Z":36.005},"Angles":{"W":0.897666,"X":0.0,"Y":0.0,"Z":-0.440677}},"ID":1881866286},{"WCID":8418,"Position":{"ObjCellID":45089102,"Origin":{"X":50.0,"Y":-54.837,"Z":36.005},"Angles":{"W":1.0,"X":0.0,"Y":0.0,"Z":0.0}},"ID":1881866287},{"WCID":7983,"Position":{"ObjCellID":45089102,"Origin":{"X":50.0413,"Y":-52.9644,"Z":36.121},"Angles":{"W":0.013384,"X":0.0,"Y":0.0,"Z":0.99991}},"ID":1881866288},{"WCID":8887,"Position":{"ObjCellID":45089103,"Origin":{"X":50.0,"Y":-60.0,"Z":36.0},"Angles":{"W":1.0,"X":0.0,"Y":0.0,"Z":0.0}},"ID":1881866289},{"WCID":8887,"Position":{"ObjCellID":45089103,"Origin":{"X":46.7737,"Y":-59.7486,"Z":36.005},"Angles":{"W":-0.668753,"X":0.0,"Y":0.0,"Z":0.743484}},"ID":1881866290},{"WCID":8887,"Position":{"ObjCellID":45089103,"Origin":{"X":49.9259,"Y":-63.0495,"Z":36.005},"Angles":{"W":-0.668753,"X":0.0,"Y":0.0,"Z":0.743484}},"ID":1881866291},{"WCID":8887,"Position":{"ObjCellID":45089103,"Origin":{"X":53.064,"Y":-60.1054,"Z":36.005},"Angles":{"W":-0.722583,"X":0.0,"Y":0.0,"Z":0.691285}},"ID":1881866292},{"WCID":8887,"Position":{"ObjCellID":45089103,"Origin":{"X":49.986,"Y":-57.1239,"Z":36.0},"Angles":{"W":1.0,"X":0.0,"Y":0.0,"Z":0.0}},"ID":1881866293},{"WCID":8418,"Position":{"ObjCellID":45089108,"Origin":{"X":50.0,"Y":-65.163,"Z":36.005},"Angles":{"W":-4.37114E-08,"X":0.0,"Y":0.0,"Z":-1.0}},"ID":1881866294},{"WCID":7983,"Position":{"ObjCellID":45089108,"Origin":{"X":49.9344,"Y":-67.0104,"Z":36.0898},"Angles":{"W":-0.999678,"X":0.0,"Y":0.0,"Z":0.025367}},"ID":1881866295},{"WCID":8887,"Position":{"ObjCellID":45089109,"Origin":{"X":49.4276,"Y":-80.5551,"Z":36.0},"Angles":{"W":0.707107,"X":0.0,"Y":0.0,"Z":-0.707107}},"ID":1881866296},{"WCID":8887,"Position":{"ObjCellID":45089110,"Origin":{"X":50.0,"Y":-90.0,"Z":36.0},"Angles":{"W":-4.37114E-08,"X":0.0,"Y":0.0,"Z":-1.0}},"ID":1881866297},{"WCID":269,"Position":{"ObjCellID":45089115,"Origin":{"X":56.7073,"Y":2.36056,"Z":40.728},"Angles":{"W":-0.873181,"X":0.0,"Y":0.0,"Z":-0.487396}},"ID":1881866298},{"WCID":23091,"Position":{"ObjCellID":45089115,"Origin":{"X":60.6355,"Y":0.505315,"Z":36.3964},"Angles":{"W":0.370876,"X":0.0,"Y":0.0,"Z":-0.928682}},"ID":1881866299},{"WCID":23091,"Position":{"ObjCellID":45089115,"Origin":{"X":58.6815,"Y":0.45936,"Z":37.1033},"Angles":{"W":0.276309,"X":0.0,"Y":0.0,"Z":-0.961069}},"ID":1881866300},{"WCID":8887,"Position":{"ObjCellID":45089115,"Origin":{"X":61.1547,"Y":-0.666667,"Z":36.0},"Angles":{"W":1.0,"X":0.0,"Y":0.0,"Z":0.0}},"ID":1881866301},{"WCID":8887,"Position":{"ObjCellID":45089116,"Origin":{"X":60.0496,"Y":-12.7127,"Z":36.005},"Angles":{"W":-0.0125363,"X":0.0,"Y":0.0,"Z":-0.999921}},"ID":1881866302},{"WCID":8887,"Position":{"ObjCellID":45089117,"Origin":{"X":59.9797,"Y":-9.21012,"Z":36.0},"Angles":{"W":-0.707107,"X":0.0,"Y":0.0,"Z":-0.707107}},"ID":1881866303},{"WCID":8887,"Position":{"ObjCellID":45089118,"Origin":{"X":60.03,"Y":-17.215,"Z":36.005},"Angles":{"W":-0.0958051,"X":0.0,"Y":0.0,"Z":-0.9954}},"ID":1881866304},{"WCID":8887,"Position":{"ObjCellID":45089118,"Origin":{"X":57.2319,"Y":-19.9606,"Z":36.005},"Angles":{"W":-0.641862,"X":0.0,"Y":0.0,"Z":-0.76682}},"ID":1881866305},{"WCID":8418,"Position":{"ObjCellID":45089121,"Origin":{"X":60.0,"Y":-54.046,"Z":36.005},"Angles":{"W":1.0,"X":0.0,"Y":0.0,"Z":0.0}},"ID":1881866306},{"WCID":7983,"Position":{"ObjCellID":45089121,"Origin":{"X":60.0,"Y":-53.0038,"Z":36.0722},"Angles":{"W":0.0,"X":0.0,"Y":0.0,"Z":-1.0}},"ID":1881866307},{"WCID":8887,"Position":{"ObjCellID":45089122,"Origin":{"X":63.1849,"Y":-57.4676,"Z":36.005},"Angles":{"W":0.998165,"X":0.0,"Y":0.0,"Z":0.060558}},"ID":1881866308},{"WCID":8887,"Position":{"ObjCellID":45089122,"Origin":{"X":57.5301,"Y":-57.5422,"Z":36.005},"Angles":{"W":0.998165,"X":0.0,"Y":0.0,"Z":0.060558}},"ID":1881866309},{"WCID":8887,"Position":{"ObjCellID":45089122,"Origin":{"X":60.0,"Y":-60.0,"Z":36.0},"Angles":{"W":-0.707107,"X":0.0,"Y":0.0,"Z":-0.707107}},"ID":1881866310},{"WCID":8887,"Position":{"ObjCellID":45089122,"Origin":{"X":63.0685,"Y":-63.2336,"Z":36.0},"Angles":{"W":-0.707107,"X":0.0,"Y":0.0,"Z":-0.707107}},"ID":1881866311},{"WCID":8887,"Position":{"ObjCellID":45089122,"Origin":{"X":56.8714,"Y":-62.9665,"Z":36.0},"Angles":{"W":-0.707107,"X":0.0,"Y":0.0,"Z":-0.707107}},"ID":1881866312},{"WCID":8418,"Position":{"ObjCellID":45089123,"Origin":{"X":60.0,"Y":-65.954,"Z":36.005},"Angles":{"W":-4.37114E-08,"X":0.0,"Y":0.0,"Z":-1.0}},"ID":1881866313},{"WCID":7983,"Position":{"ObjCellID":45089123,"Origin":{"X":60.0,"Y":-66.9737,"Z":36.0444},"Angles":{"W":1.0,"X":0.0,"Y":0.0,"Z":-4.37114E-08}},"ID":1881866314},{"WCID":8887,"Position":{"ObjCellID":45089127,"Origin":{"X":60.0,"Y":-110.0,"Z":36.005},"Angles":{"W":1.0,"X":0.0,"Y":0.0,"Z":0.0}},"ID":1881866315},{"WCID":8887,"Position":{"ObjCellID":45089128,"Origin":{"X":59.9463,"Y":-106.723,"Z":36.005},"Angles":{"W":-0.999892,"X":0.0,"Y":0.0,"Z":-0.01472}},"ID":1881866316},{"WCID":7983,"Position":{"ObjCellID":45089129,"Origin":{"X":59.9983,"Y":-120.689,"Z":36.9308},"Angles":{"W":0.972615,"X":0.0,"Y":0.0,"Z":-0.232422}},"ID":1881866317},{"WCID":23091,"Position":{"ObjCellID":45089129,"Origin":{"X":58.5764,"Y":-119.26,"Z":36.9474},"Angles":{"W":-0.999923,"X":0.0,"Y":0.0,"Z":0.0123991}},"ID":1881866318},{"WCID":8887,"Position":{"ObjCellID":45089129,"Origin":{"X":61.5396,"Y":-119.111,"Z":36.005},"Angles":{"W":1.0,"X":0.0,"Y":0.0,"Z":0.0}},"ID":1881866319},{"WCID":8887,"Position":{"ObjCellID":45089130,"Origin":{"X":68.8453,"Y":-0.666667,"Z":36.0},"Angles":{"W":0.707107,"X":0.0,"Y":0.0,"Z":-0.707107}},"ID":1881866320},{"WCID":8887,"Position":{"ObjCellID":45089131,"Origin":{"X":70.0488,"Y":-9.38146,"Z":36.0},"Angles":{"W":-4.37114E-08,"X":0.0,"Y":0.0,"Z":-1.0}},"ID":1881866321},{"WCID":8887,"Position":{"ObjCellID":45089132,"Origin":{"X":70.0274,"Y":-13.1142,"Z":36.005},"Angles":{"W":-0.999994,"X":0.0,"Y":0.0,"Z":-0.00340196}},"ID":1881866322},{"WCID":8887,"Position":{"ObjCellID":45089133,"Origin":{"X":70.0337,"Y":-16.9979,"Z":36.005},"Angles":{"W":-0.999949,"X":0.0,"Y":0.0,"Z":0.010051}},"ID":1881866323},{"WCID":8887,"Position":{"ObjCellID":45089134,"Origin":{"X":73.0805,"Y":-19.9769,"Z":36.005},"Angles":{"W":-0.737848,"X":0.0,"Y":0.0,"Z":-0.674967}},"ID":1881866324},{"WCID":8418,"Position":{"ObjCellID":45089136,"Origin":{"X":70.0,"Y":-54.046,"Z":36.005},"Angles":{"W":1.0,"X":0.0,"Y":0.0,"Z":0.0}},"ID":1881866325},{"WCID":7983,"Position":{"ObjCellID":45089136,"Origin":{"X":70.0,"Y":-53.0191,"Z":36.0534},"Angles":{"W":0.0,"X":0.0,"Y":0.0,"Z":-1.0}},"ID":1881866326},{"WCID":8887,"Position":{"ObjCellID":45089137,"Origin":{"X":70.0,"Y":-60.0,"Z":36.0},"Angles":{"W":0.707107,"X":0.0,"Y":0.0,"Z":-0.707107}},"ID":1881866327},{"WCID":8887,"Position":{"ObjCellID":45089137,"Origin":{"X":73.0525,"Y":-62.9255,"Z":36.0},"Angles":{"W":0.707107,"X":0.0,"Y":0.0,"Z":-0.707107}},"ID":1881866328},{"WCID":8887,"Position":{"ObjCellID":45089137,"Origin":{"X":72.798,"Y":-57.1931,"Z":36.0},"Angles":{"W":0.707107,"X":0.0,"Y":0.0,"Z":-0.707107}},"ID":1881866329},{"WCID":8887,"Position":{"ObjCellID":45089137,"Origin":{"X":66.7793,"Y":-57.4643,"Z":36.0},"Angles":{"W":0.707107,"X":0.0,"Y":0.0,"Z":-0.707107}},"ID":1881866330},{"WCID":8887,"Position":{"ObjCellID":45089137,"Origin":{"X":66.7588,"Y":-63.0753,"Z":36.0},"Angles":{"W":0.707107,"X":0.0,"Y":0.0,"Z":-0.707107}},"ID":1881866331},{"WCID":8418,"Position":{"ObjCellID":45089138,"Origin":{"X":70.0,"Y":-65.954,"Z":36.005},"Angles":{"W":-4.37114E-08,"X":0.0,"Y":0.0,"Z":-1.0}},"ID":1881866332},{"WCID":7983,"Position":{"ObjCellID":45089138,"Origin":{"X":70.0,"Y":-66.9737,"Z":36.0444},"Angles":{"W":1.0,"X":0.0,"Y":0.0,"Z":-4.37114E-08}},"ID":1881866333},{"WCID":8887,"Position":{"ObjCellID":45089139,"Origin":{"X":70.1111,"Y":-102.874,"Z":36.005},"Angles":{"W":0.0171665,"X":0.0,"Y":0.0,"Z":-0.999853}},"ID":1881866334},{"WCID":8887,"Position":{"ObjCellID":45089141,"Origin":{"X":73.7309,"Y":-100.093,"Z":36.005},"Angles":{"W":-0.662845,"X":0.0,"Y":0.0,"Z":-0.748757}},"ID":1881866335},{"WCID":23091,"Position":{"ObjCellID":45089142,"Origin":{"X":69.4104,"Y":-107.442,"Z":36.0055},"Angles":{"W":0.987231,"X":0.0,"Y":0.0,"Z":-0.159296}},"ID":1881866336},{"WCID":8887,"Position":{"ObjCellID":45089142,"Origin":{"X":70.0577,"Y":-106.924,"Z":36.005},"Angles":{"W":0.0171665,"X":0.0,"Y":0.0,"Z":-0.999853}},"ID":1881866337},{"WCID":8887,"Position":{"ObjCellID":45089143,"Origin":{"X":70.0,"Y":-110.0,"Z":36.005},"Angles":{"W":1.0,"X":0.0,"Y":0.0,"Z":0.0}},"ID":1881866338},{"WCID":8887,"Position":{"ObjCellID":45089144,"Origin":{"X":68.4604,"Y":-119.111,"Z":36.005},"Angles":{"W":1.0,"X":0.0,"Y":0.0,"Z":-4.37114E-08}},"ID":1881866339},{"WCID":8887,"Position":{"ObjCellID":45089145,"Origin":{"X":79.8879,"Y":-22.95,"Z":36.005},"Angles":{"W":-1.0,"X":0.0,"Y":0.0,"Z":-0.0003}},"ID":1881866340},{"WCID":8887,"Position":{"ObjCellID":45089145,"Origin":{"X":77.204,"Y":-20.0968,"Z":36.005},"Angles":{"W":-0.74172,"X":0.0,"Y":0.0,"Z":-0.67071}},"ID":1881866341},{"WCID":7983,"Position":{"ObjCellID":45089148,"Origin":{"X":81.3605,"Y":-30.1911,"Z":36.005},"Angles":{"W":-0.302468,"X":0.0,"Y":0.0,"Z":0.95316}},"ID":1881866342},{"WCID":8887,"Position":{"ObjCellID":45089148,"Origin":{"X":80.0152,"Y":-31.8833,"Z":36.005},"Angles":{"W":-0.999786,"X":0.0,"Y":0.0,"Z":-0.020702}},"ID":1881866343},{"WCID":8887,"Position":{"ObjCellID":45089149,"Origin":{"X":79.8541,"Y":-27.8539,"Z":36.005},"Angles":{"W":-0.999146,"X":0.0,"Y":0.0,"Z":0.041318}},"ID":1881866344},{"WCID":8887,"Position":{"ObjCellID":45089150,"Origin":{"X":81.5396,"Y":-39.1111,"Z":36.005},"Angles":{"W":1.0,"X":0.0,"Y":0.0,"Z":0.0}},"ID":1881866345},{"WCID":8418,"Position":{"ObjCellID":45089151,"Origin":{"X":80.0,"Y":-54.837,"Z":36.005},"Angles":{"W":1.0,"X":0.0,"Y":0.0,"Z":0.0}},"ID":1881866346},{"WCID":7983,"Position":{"ObjCellID":45089151,"Origin":{"X":80.0,"Y":-53.0466,"Z":36.0194},"Angles":{"W":0.0,"X":0.0,"Y":0.0,"Z":-1.0}},"ID":1881866347},{"WCID":8887,"Position":{"ObjCellID":45089152,"Origin":{"X":80.0,"Y":-60.0,"Z":36.0},"Angles":{"W":1.0,"X":0.0,"Y":0.0,"Z":0.0}},"ID":1881866348},{"WCID":8887,"Position":{"ObjCellID":45089152,"Origin":{"X":76.9963,"Y":-60.0402,"Z":36.005},"Angles":{"W":-0.726793,"X":0.0,"Y":0.0,"Z":0.686857}},"ID":1881866349},{"WCID":8887,"Position":{"ObjCellID":45089152,"Origin":{"X":80.1492,"Y":-63.1129,"Z":36.0},"Angles":{"W":1.0,"X":0.0,"Y":0.0,"Z":0.0}},"ID":1881866350},{"WCID":8887,"Position":{"ObjCellID":45089152,"Origin":{"X":83.4253,"Y":-59.9269,"Z":36.0},"Angles":{"W":1.0,"X":0.0,"Y":0.0,"Z":0.0}},"ID":1881866351},{"WCID":8887,"Position":{"ObjCellID":45089152,"Origin":{"X":79.7944,"Y":-56.8367,"Z":36.0},"Angles":{"W":1.0,"X":0.0,"Y":0.0,"Z":0.0}},"ID":1881866352},{"WCID":8418,"Position":{"ObjCellID":45089157,"Origin":{"X":80.0,"Y":-65.163,"Z":36.005},"Angles":{"W":-4.37114E-08,"X":0.0,"Y":0.0,"Z":-1.0}},"ID":1881866353},{"WCID":7983,"Position":{"ObjCellID":45089157,"Origin":{"X":80.0,"Y":-67.0228,"Z":36.1051},"Angles":{"W":1.0,"X":0.0,"Y":0.0,"Z":-4.37114E-08}},"ID":1881866354},{"WCID":7983,"Position":{"ObjCellID":45089158,"Origin":{"X":76.8014,"Y":-81.6416,"Z":38.0717},"Angles":{"W":0.795688,"X":0.0,"Y":0.0,"Z":-0.605707}},"ID":1881866355},{"WCID":8887,"Position":{"ObjCellID":45089158,"Origin":{"X":81.5396,"Y":-80.8889,"Z":36.005},"Angles":{"W":1.0,"X":0.0,"Y":0.0,"Z":0.0}},"ID":1881866356},{"WCID":8887,"Position":{"ObjCellID":45089159,"Origin":{"X":79.9416,"Y":-93.8057,"Z":36.005},"Angles":{"W":0.00936423,"X":0.0,"Y":0.0,"Z":0.999956}},"ID":1881866357},{"WCID":8887,"Position":{"ObjCellID":45089160,"Origin":{"X":80.0,"Y":-90.0,"Z":36.005},"Angles":{"W":1.0,"X":0.0,"Y":0.0,"Z":0.0}},"ID":1881866358},{"WCID":8887,"Position":{"ObjCellID":45089161,"Origin":{"X":77.4366,"Y":-100.001,"Z":36.0},"Angles":{"W":0.707107,"X":0.0,"Y":0.0,"Z":-0.707107}},"ID":1881866359},{"WCID":8887,"Position":{"ObjCellID":45089161,"Origin":{"X":79.9452,"Y":-97.1721,"Z":36.0},"Angles":{"W":0.707107,"X":0.0,"Y":0.0,"Z":-0.707107}},"ID":1881866360},{"WCID":7983,"Position":{"ObjCellID":45089162,"Origin":{"X":79.2785,"Y":-96.5386,"Z":36.005},"Angles":{"W":0.972472,"X":0.0,"Y":0.0,"Z":-0.233019}},"ID":1881866361},{"WCID":8887,"Position":{"ObjCellID":45089164,"Origin":{"X":89.5218,"Y":-27.2767,"Z":38.1187},"Angles":{"W":0.968912,"X":0.0,"Y":0.0,"Z":0.247404}},"ID":1881866362},{"WCID":7983,"Position":{"ObjCellID":45089165,"Origin":{"X":89.631,"Y":-39.5204,"Z":36.005},"Angles":{"W":0.942493,"X":0.0,"Y":0.0,"Z":0.334225}},"ID":1881866363},{"WCID":8887,"Position":{"ObjCellID":45089165,"Origin":{"X":90.0,"Y":-40.0,"Z":36.0},"Angles":{"W":-4.37114E-08,"X":0.0,"Y":0.0,"Z":-1.0}},"ID":1881866364},{"WCID":8887,"Position":{"ObjCellID":45089166,"Origin":{"X":90.0167,"Y":-42.2536,"Z":36.005},"Angles":{"W":0.024531,"X":0.0,"Y":0.0,"Z":-0.999699}},"ID":1881866365},{"WCID":8887,"Position":{"ObjCellID":45089167,"Origin":{"X":90.0,"Y":-50.0,"Z":36.0},"Angles":{"W":1.0,"X":0.0,"Y":0.0,"Z":0.0}},"ID":1881866366},{"WCID":8887,"Position":{"ObjCellID":45089167,"Origin":{"X":89.8047,"Y":-53.3362,"Z":36.005},"Angles":{"W":0.999993,"X":0.0,"Y":0.0,"Z":0.003737}},"ID":1881866367},{"WCID":8887,"Position":{"ObjCellID":45089167,"Origin":{"X":89.9045,"Y":-47.0205,"Z":36.005},"Angles":{"W":0.999993,"X":0.0,"Y":0.0,"Z":0.003737}},"ID":1881866368},{"WCID":8887,"Position":{"ObjCellID":45089168,"Origin":{"X":90.0,"Y":-60.0,"Z":36.0},"Angles":{"W":1.0,"X":0.0,"Y":0.0,"Z":0.0}},"ID":1881866369},{"WCID":8887,"Position":{"ObjCellID":45089168,"Origin":{"X":89.8362,"Y":-56.8332,"Z":36.005},"Angles":{"W":0.998664,"X":0.0,"Y":0.0,"Z":0.051678}},"ID":1881866370},{"WCID":8887,"Position":{"ObjCellID":45089168,"Origin":{"X":89.8903,"Y":-63.5046,"Z":36.005},"Angles":{"W":-0.035583,"X":0.0,"Y":0.0,"Z":0.999367}},"ID":1881866371},{"WCID":8887,"Position":{"ObjCellID":45089168,"Origin":{"X":93.4176,"Y":-59.9556,"Z":36.005},"Angles":{"W":-0.720924,"X":0.0,"Y":0.0,"Z":0.693014}},"ID":1881866372},{"WCID":8887,"Position":{"ObjCellID":45089168,"Origin":{"X":86.7078,"Y":-59.9985,"Z":36.005},"Angles":{"W":-0.685387,"X":0.0,"Y":0.0,"Z":0.728179}},"ID":1881866373},{"WCID":7983,"Position":{"ObjCellID":45089173,"Origin":{"X":90.2699,"Y":-71.6072,"Z":36.005},"Angles":{"W":0.99875,"X":0.0,"Y":0.0,"Z":0.049979}},"ID":1881866374},{"WCID":8887,"Position":{"ObjCellID":45089173,"Origin":{"X":90.0,"Y":-70.0,"Z":36.0},"Angles":{"W":-4.37114E-08,"X":0.0,"Y":0.0,"Z":-1.0}},"ID":1881866375},{"WCID":8887,"Position":{"ObjCellID":45089173,"Origin":{"X":89.9701,"Y":-66.8272,"Z":36.005},"Angles":{"W":-0.0384959,"X":0.0,"Y":0.0,"Z":0.999259}},"ID":1881866376},{"WCID":8887,"Position":{"ObjCellID":45089173,"Origin":{"X":90.0478,"Y":-73.1681,"Z":36.005},"Angles":{"W":-0.013505,"X":0.0,"Y":0.0,"Z":0.999909}},"ID":1881866377},{"WCID":8887,"Position":{"ObjCellID":45089174,"Origin":{"X":90.0641,"Y":-76.7419,"Z":36.005},"Angles":{"W":-0.013505,"X":0.0,"Y":0.0,"Z":0.999909}},"ID":1881866378},{"WCID":8887,"Position":{"ObjCellID":45089175,"Origin":{"X":90.0,"Y":-80.0,"Z":36.005},"Angles":{"W":1.0,"X":0.0,"Y":0.0,"Z":0.0}},"ID":1881866379},{"WCID":8887,"Position":{"ObjCellID":45089176,"Origin":{"X":88.4604,"Y":-89.1111,"Z":36.005},"Angles":{"W":1.0,"X":0.0,"Y":0.0,"Z":-4.37114E-08}},"ID":1881866380},{"WCID":8410,"Position":{"ObjCellID":45089177,"Origin":{"X":95.96,"Y":-60.0,"Z":36.005},"Angles":{"W":-0.707107,"X":0.0,"Y":0.0,"Z":-0.707107}},"ID":1881866381},{"WCID":2131,"Position":{"ObjCellID":45089177,"Origin":{"X":98.4876,"Y":-60.0173,"Z":36.005},"Angles":{"W":-0.707107,"X":0.0,"Y":0.0,"Z":-0.707107}},"ID":1881866382},{"WCID":8887,"Position":{"ObjCellID":45089177,"Origin":{"X":100.0,"Y":-60.0,"Z":36.0},"Angles":{"W":0.707107,"X":0.0,"Y":0.0,"Z":-0.707107}},"ID":1881866383},{"WCID":8887,"Position":{"ObjCellID":45089177,"Origin":{"X":103.179,"Y":-59.8997,"Z":36.005},"Angles":{"W":0.691029,"X":0.0,"Y":0.0,"Z":0.722827}},"ID":1881866384},{"WCID":8887,"Position":{"ObjCellID":45089177,"Origin":{"X":96.7301,"Y":-60.0123,"Z":36.005},"Angles":{"W":0.691029,"X":0.0,"Y":0.0,"Z":0.722827}},"ID":1881866385},{"WCID":8418,"Position":{"ObjCellID":45089178,"Origin":{"X":110.0,"Y":-54.837,"Z":36.005},"Angles":{"W":1.0,"X":0.0,"Y":0.0,"Z":0.0}},"ID":1881866386},{"WCID":7983,"Position":{"ObjCellID":45089178,"Origin":{"X":110.035,"Y":-53.0155,"Z":36.0891},"Angles":{"W":0.025651,"X":0.0,"Y":0.0,"Z":-0.999671}},"ID":1881866387},{"WCID":8887,"Position":{"ObjCellID":45089179,"Origin":{"X":110.0,"Y":-60.0,"Z":36.0},"Angles":{"W":1.0,"X":0.0,"Y":0.0,"Z":0.0}},"ID":1881866388},{"WCID":8887,"Position":{"ObjCellID":45089179,"Origin":{"X":113.076,"Y":-59.9575,"Z":36.0},"Angles":{"W":1.0,"X":0.0,"Y":0.0,"Z":0.0}},"ID":1881866389},{"WCID":8887,"Position":{"ObjCellID":45089179,"Origin":{"X":109.948,"Y":-63.0234,"Z":36.0},"Angles":{"W":1.0,"X":0.0,"Y":0.0,"Z":0.0}},"ID":1881866390},{"WCID":8887,"Position":{"ObjCellID":45089179,"Origin":{"X":109.918,"Y":-57.018,"Z":36.0},"Angles":{"W":1.0,"X":0.0,"Y":0.0,"Z":0.0}},"ID":1881866391},{"WCID":8887,"Position":{"ObjCellID":45089179,"Origin":{"X":106.91,"Y":-59.949,"Z":36.0},"Angles":{"W":1.0,"X":0.0,"Y":0.0,"Z":0.0}},"ID":1881866392},{"WCID":8418,"Position":{"ObjCellID":45089184,"Origin":{"X":110.0,"Y":-65.163,"Z":36.005},"Angles":{"W":-4.37114E-08,"X":0.0,"Y":0.0,"Z":-1.0}},"ID":1881866393},{"WCID":7983,"Position":{"ObjCellID":45089184,"Origin":{"X":110.055,"Y":-66.9984,"Z":36.092},"Angles":{"W":0.999924,"X":0.0,"Y":0.0,"Z":-0.012356}},"ID":1881866394},{"WCID":8887,"Position":{"ObjCellID":45089185,"Origin":{"X":119.241,"Y":-60.0617,"Z":36.0},"Angles":{"W":-0.707107,"X":0.0,"Y":0.0,"Z":-0.707107}},"ID":1881866395},{"WCID":8410,"Position":{"ObjCellID":45089189,"Origin":{"X":115.218,"Y":-60.0,"Z":36.005},"Angles":{"W":-0.707107,"X":0.0,"Y":0.0,"Z":-0.707107}},"ID":1881866396},{"WCID":8887,"Position":{"ObjCellID":45089189,"Origin":{"X":116.762,"Y":-60.0053,"Z":36.005},"Angles":{"W":0.732312,"X":0.0,"Y":0.0,"Z":0.680969}},"ID":1881866397},{"WCID":8887,"Position":{"ObjCellID":45089191,"Origin":{"X":17.8027,"Y":-50.0689,"Z":42.005},"Angles":{"W":0.721029,"X":0.0,"Y":0.0,"Z":0.692905}},"ID":1881866398},{"WCID":8887,"Position":{"ObjCellID":45089193,"Origin":{"X":19.9689,"Y":-53.2024,"Z":42.005},"Angles":{"W":0.999409,"X":0.0,"Y":0.0,"Z":0.034375}},"ID":1881866399},{"WCID":8887,"Position":{"ObjCellID":45089194,"Origin":{"X":22.0927,"Y":-59.8587,"Z":42.0},"Angles":{"W":-0.707107,"X":0.0,"Y":0.0,"Z":-0.707107}},"ID":1881866400},{"WCID":8887,"Position":{"ObjCellID":45089194,"Origin":{"X":20.0372,"Y":-56.5332,"Z":42.005},"Angles":{"W":0.999926,"X":0.0,"Y":0.0,"Z":-0.0121431}},"ID":1881866401},{"WCID":8887,"Position":{"ObjCellID":45089194,"Origin":{"X":19.9954,"Y":-63.2106,"Z":42.005},"Angles":{"W":0.999926,"X":0.0,"Y":0.0,"Z":-0.0121431}},"ID":1881866402},{"WCID":8887,"Position":{"ObjCellID":45089197,"Origin":{"X":24.9147,"Y":-59.9823,"Z":42.005},"Angles":{"W":0.999926,"X":0.0,"Y":0.0,"Z":-0.0121431}},"ID":1881866403},{"WCID":7983,"Position":{"ObjCellID":45089198,"Origin":{"X":19.8367,"Y":-66.1504,"Z":42.005},"Angles":{"W":-0.999983,"X":0.0,"Y":0.0,"Z":-0.00590395}},"ID":1881866404},{"WCID":8887,"Position":{"ObjCellID":45089198,"Origin":{"X":19.8545,"Y":-66.4932,"Z":42.005},"Angles":{"W":0.999926,"X":0.0,"Y":0.0,"Z":-0.012143}},"ID":1881866405},{"WCID":7983,"Position":{"ObjCellID":45089226,"Origin":{"X":0.827492,"Y":-50.047,"Z":48.005},"Angles":{"W":0.23933,"X":0.0,"Y":0.0,"Z":0.970938}},"ID":1881866406},{"WCID":8418,"Position":{"ObjCellID":45089227,"Origin":{"X":-1.34039E-07,"Y":-53.916,"Z":48.005},"Angles":{"W":1.0,"X":0.0,"Y":0.0,"Z":0.0}},"ID":1881866407},{"WCID":23089,"Position":{"ObjCellID":45089232,"Origin":{"X":-2.05508,"Y":-68.5844,"Z":48.005},"Angles":{"W":-0.768266,"X":0.0,"Y":0.0,"Z":0.64013}},"ID":1881866408},{"WCID":23089,"Position":{"ObjCellID":45089236,"Origin":{"X":-2.20359,"Y":-83.8243,"Z":48.005},"Angles":{"W":-0.947208,"X":0.0,"Y":0.0,"Z":0.320619}},"ID":1881866409},{"WCID":7983,"Position":{"ObjCellID":45089260,"Origin":{"X":19.3293,"Y":-79.8241,"Z":48.005},"Angles":{"W":0.971375,"X":0.0,"Y":0.0,"Z":-0.237551}},"ID":1881866410},{"WCID":5624,"Position":{"ObjCellID":45089273,"Origin":{"X":20.01,"Y":-64.85,"Z":54.0},"Angles":{"W":1.0,"X":0.0,"Y":0.0,"Z":-4.37114E-08}},"ID":1881866411},{"WCID":23091,"Position":{"ObjCellID":45089273,"Origin":{"X":20.0276,"Y":-63.5281,"Z":54.0055},"Angles":{"W":-0.012425,"X":0.0,"Y":0.0,"Z":-0.999923}},"ID":1881866412},{"WCID":5624,"Position":{"ObjCellID":45089282,"Origin":{"X":19.99,"Y":-85.15,"Z":54.0},"Angles":{"W":0.0,"X":0.0,"Y":0.0,"Z":-1.0}},"ID":1881866413},{"WCID":23091,"Position":{"ObjCellID":45089282,"Origin":{"X":19.9905,"Y":-86.5115,"Z":54.0055},"Angles":{"W":1.0,"X":0.0,"Y":0.0,"Z":0.0}},"ID":1881866414},{"WCID":5624,"Position":{"ObjCellID":45089283,"Origin":{"X":30.01,"Y":-64.85,"Z":54.0},"Angles":{"W":1.0,"X":0.0,"Y":0.0,"Z":-4.37114E-08}},"ID":1881866415},{"WCID":23091,"Position":{"ObjCellID":45089283,"Origin":{"X":29.9696,"Y":-63.2973,"Z":54.0055},"Angles":{"W":-0.00889006,"X":0.0,"Y":0.0,"Z":-0.99996}},"ID":1881866416},{"WCID":5624,"Position":{"ObjCellID":45089292,"Origin":{"X":29.99,"Y":-85.15,"Z":54.0},"Angles":{"W":0.0,"X":0.0,"Y":0.0,"Z":-1.0}},"ID":1881866417},{"WCID":23091,"Position":{"ObjCellID":45089292,"Origin":{"X":29.9518,"Y":-86.5496,"Z":54.0055},"Angles":{"W":-0.999864,"X":0.0,"Y":0.0,"Z":0.016479}},"ID":1881866418},{"WCID":23089,"Position":{"ObjCellID":45089297,"Origin":{"X":53.0771,"Y":-60.1993,"Z":54.005},"Angles":{"W":-0.704138,"X":0.0,"Y":0.0,"Z":0.710063}},"ID":1881866419},{"WCID":23089,"Position":{"ObjCellID":45089299,"Origin":{"X":60.1,"Y":-52.9231,"Z":54.005},"Angles":{"W":-0.0260621,"X":0.0,"Y":0.0,"Z":-0.99966}},"ID":1881866420},{"WCID":23089,"Position":{"ObjCellID":45089301,"Origin":{"X":60.042,"Y":-66.7735,"Z":54.005},"Angles":{"W":-0.999884,"X":0.0,"Y":0.0,"Z":0.015255}},"ID":1881866421},{"WCID":7983,"Position":{"ObjCellID":45089317,"Origin":{"X":100.429,"Y":-60.1192,"Z":54.005},"Angles":{"W":-0.740055,"X":0.0,"Y":0.0,"Z":0.672546}},"ID":1881866422},{"WCID":23091,"Position":{"ObjCellID":45089320,"Origin":{"X":107.755,"Y":-56.3702,"Z":54.0055},"Angles":{"W":-0.599541,"X":0.0,"Y":0.0,"Z":0.800344}},"ID":1881866423},{"WCID":23091,"Position":{"ObjCellID":45089320,"Origin":{"X":108.887,"Y":-63.3225,"Z":54.0055},"Angles":{"W":-0.740055,"X":0.0,"Y":0.0,"Z":0.672546}},"ID":1881866424},{"WCID":7983,"Position":{"ObjCellID":45089322,"Origin":{"X":119.29,"Y":-41.1329,"Z":54.005},"Angles":{"W":0.07526,"X":0.0,"Y":0.0,"Z":-0.997164}},"ID":1881866425},{"WCID":23091,"Position":{"ObjCellID":45089325,"Origin":{"X":122.15,"Y":-67.7062,"Z":54.0055},"Angles":{"W":0.894372,"X":0.0,"Y":0.0,"Z":0.447324}},"ID":1881866426},{"WCID":23091,"Position":{"ObjCellID":45089328,"Origin":{"X":131.76,"Y":-58.1817,"Z":54.0055},"Angles":{"W":0.675298,"X":0.0,"Y":0.0,"Z":-0.737545}},"ID":1881866427},{"WCID":7983,"Position":{"ObjCellID":45089335,"Origin":{"X":139.634,"Y":-61.7998,"Z":54.005},"Angles":{"W":0.790251,"X":0.0,"Y":0.0,"Z":-0.612784}},"ID":1881866428},{"WCID":2609,"Position":{"ObjCellID":45089341,"Origin":{"X":160.0,"Y":-60.0,"Z":54.0},"Angles":{"W":0.707107,"X":0.0,"Y":0.0,"Z":-0.707107}},"ID":1881866429},{"WCID":23089,"Position":{"ObjCellID":45089341,"Origin":{"X":158.619,"Y":-57.6605,"Z":54.005},"Angles":{"W":0.260117,"X":0.0,"Y":0.0,"Z":-0.965577}},"ID":1881866430},{"WCID":23089,"Position":{"ObjCellID":45089342,"Origin":{"X":157.511,"Y":-71.592,"Z":54.005},"Angles":{"W":-0.98793,"X":0.0,"Y":0.0,"Z":0.154904}},"ID":1881866431},{"WCID":23089,"Position":{"ObjCellID":45089342,"Origin":{"X":163.084,"Y":-74.1368,"Z":54.005},"Angles":{"W":-0.992872,"X":0.0,"Y":0.0,"Z":-0.119186}},"ID":1881866432},{"WCID":7983,"Position":{"ObjCellID":45089343,"Origin":{"X":160.003,"Y":-79.2942,"Z":54.005},"Angles":{"W":-0.999534,"X":0.0,"Y":0.0,"Z":0.030526}},"ID":1881866433},{"WCID":23089,"Position":{"ObjCellID":45089344,"Origin":{"X":167.118,"Y":-48.9352,"Z":54.005},"Angles":{"W":0.352698,"X":0.0,"Y":0.0,"Z":-0.935737}},"ID":1881866434},{"WCID":2131,"Position":{"ObjCellID":45089407,"Origin":{"X":230.12,"Y":-50.0,"Z":72.005},"Angles":{"W":0.923879,"X":0.0,"Y":0.0,"Z":-0.382684}},"ID":1881866435},{"WCID":8548,"Position":{"ObjCellID":45089407,"Origin":{"X":230.0,"Y":-50.0,"Z":73.2355},"Angles":{"W":0.696707,"X":0.0,"Y":0.0,"Z":-0.717356}},"ID":1881866436},{"WCID":4456,"Position":{"ObjCellID":45089411,"Origin":{"X":234.413,"Y":-50.0,"Z":72.005},"Angles":{"W":0.707107,"X":0.0,"Y":0.0,"Z":-0.707107}},"ID":1881866437},{"WCID":4460,"Position":{"ObjCellID":45089416,"Origin":{"X":234.406,"Y":-60.0,"Z":72.005},"Angles":{"W":0.707107,"X":0.0,"Y":0.0,"Z":-0.707107}},"ID":1881866438},{"WCID":7562,"Position":{"ObjCellID":45089417,"Origin":{"X":230.743,"Y":-70.0784,"Z":73.1552},"Angles":{"W":0.690705,"X":0.0,"Y":0.0,"Z":-0.723137}},"ID":1881866439},{"WCID":2131,"Position":{"ObjCellID":45089417,"Origin":{"X":230.813,"Y":-70.0009,"Z":72.005},"Angles":{"W":0.923879,"X":0.0,"Y":0.0,"Z":-0.382684}},"ID":1881866440},{"WCID":4456,"Position":{"ObjCellID":45089421,"Origin":{"X":234.412,"Y":-70.0,"Z":72.005},"Angles":{"W":0.707107,"X":0.0,"Y":0.0,"Z":-0.707107}},"ID":1881866441},{"WCID":8851,"Position":{"ObjCellID":45089447,"Origin":{"X":279.928,"Y":-60.0,"Z":72.12},"Angles":{"W":0.707107,"X":0.0,"Y":0.0,"Z":-0.707107}},"ID":1881866442}],"Links":[{"Source":1881866298,"Target":1881866396},{"Source":1881866382,"Target":1881866381},{"Source":1881866250,"Target":1881866243},{"Source":1881866251,"Target":1881866244},{"Source":1881866252,"Target":1881866243},{"Source":1881866256,"Target":1881866243},{"Source":1881866257,"Target":1881866244},{"Source":1881866258,"Target":1881866243},{"Source":1881866259,"Target":1881866243},{"Source":1881866260,"Target":1881866244},{"Source":1881866261,"Target":1881866243},{"Source":1881866253,"Target":1881866243},{"Source":1881866254,"Target":1881866244},{"Source":1881866255,"Target":1881866243},{"Source":1881866387,"Target":1881866244},{"Source":1881866394,"Target":1881866244},{"Source":1881866347,"Target":1881866244},{"Source":1881866354,"Target":1881866244},{"Source":1881866326,"Target":1881866244},{"Source":1881866333,"Target":1881866244},{"Source":1881866307,"Target":1881866244},{"Source":1881866314,"Target":1881866244},{"Source":1881866288,"Target":1881866244},{"Source":1881866295,"Target":1881866244},{"Source":1881866262,"Target":1881866244},{"Source":1881866285,"Target":1881866244},{"Source":1881866363,"Target":1881866244},{"Source":1881866342,"Target":1881866244},{"Source":1881866355,"Target":1881866244},{"Source":1881866374,"Target":1881866244},{"Source":1881866361,"Target":1881866244},{"Source":1881866317,"Target":1881866244},{"Source":1881866279,"Target":1881866244},{"Source":1881866336,"Target":1881866244},{"Source":1881866318,"Target":1881866244},{"Source":1881866299,"Target":1881866244},{"Source":1881866300,"Target":1881866244},{"Source":1881866416,"Target":1881866243},{"Source":1881866412,"Target":1881866243},{"Source":1881866414,"Target":1881866243},{"Source":1881866418,"Target":1881866243},{"Source":1881866429,"Target":1881866381},{"Source":1881866419,"Target":1881866244},{"Source":1881866421,"Target":1881866244},{"Source":1881866420,"Target":1881866244},{"Source":1881866430,"Target":1881866243},{"Source":1881866434,"Target":1881866243},{"Source":1881866431,"Target":1881866243},{"Source":1881866432,"Target":1881866243},{"Source":1881866433,"Target":1881866243},{"Source":1881866428,"Target":1881866243},{"Source":1881866427,"Target":1881866243},{"Source":1881866426,"Target":1881866243},{"Source":1881866425,"Target":1881866243},{"Source":1881866423,"Target":1881866243},{"Source":1881866424,"Target":1881866243},{"Source":1881866422,"Target":1881866243},{"Source":1881866410,"Target":1881866244},{"Source":1881866406,"Target":1881866244},{"Source":1881866404,"Target":1881866244},{"Source":1881866435,"Target":1881866436},{"Source":1881866440,"Target":1881866439},{"Source":1881866409,"Target":1881866244},{"Source":1881866408,"Target":1881866244},{"Source":1881866242,"Target":1881866243},{"Source":1881866247,"Target":1881866243},{"Source":1881866443,"Target":1881866243},{"Source":1881866444,"Target":1881866243}]}