{"Label":"Adventurers's Warning","Timestamp":1496988460,"WeenieType":8,"IntValues":{"9":0,"1":8192,"93":1044,"5":25,"16":8,"8":5,"19":20},"BoolValues":{"22":false},"DoubleValues":{"54":1.0},"StringValues":{"16":"A note left in the Mountain Fortress by a disgruntled adventurer.","1":"Adventurers's Warning","15":"A note left in the Mountain Fortress by a disgruntled adventurer."},"DIDValues":{"1":33554773,"3":536870932,"8":100668176,"22":872415275},"WCID":6116,"PagesData":{"MaxNumPages":2,"MaxNumCharsPerPage":1000,"Pages":[{"AuthorID":4294967295,"AuthorName":"Unknown","AuthorAccount":"prewritten","IgnoreAuthor":false,"Text":"\nI have spent too much time and lost too much of my life-force seeking this \"Old Man of the Mountain.\" Six times have those terrible creatures lurking in the darkness claimed my life, my weaponry, and a portion of my soul. If the Old Man seeks strong warriors to serve him, then he obviously seeks someone stronger than myself. \n\n"},{"AuthorID":4294967295,"AuthorName":"","AuthorAccount":"prewritten","IgnoreAuthor":false,"Text":"And what kind of malevolent being is he, that he associates with the shadow fiends and makes his home so near that sinister altar? Now I find it easier to believe those rumors of his dark alliance. I will leave this foul place now, never to return.\n\n"}]}}